SP4-SPDIF-AES3/rtl/clock_divisor.sv
module clock_divider#(parameter WIDTH = 16)(
			input logic 	clk2,
  			input logic    nrst,
			output logic 	clk_o
);
  logic aux;
  always_ff @(posedge clk_o or negedge nrst) begin

    if(~nrst) begin
      aux <= 0;
    end
    else begin
      aux = ~ aux;
    end
end
  assign out = aux;
  
endmodule

SP4-SPDIF-AES3/rtl/design.sv
//`include "clock_divisor.sv"

module SPDIF#(parameter WIDTH = 16)(
  			input logic     clk1,
  			input logic     clk2,
			input logic 	nrst,
  			input logic		data,             //data parallelo
  			//input logic 	[WIDTH-1:0] data, //data serial
			output logic 	dataDMC
);
  
    //Internals Variables
  logic data_first;
  
  always_ff @(posedge clk2 or posedge clk1 or negedge nrst) begin
    if (!nrst) begin
        data_first = 0;
    end
    else begin 
        data_first = dataDMC;
    end
	end
  
 	//Logical Next_State
  always_comb begin
  case(data)
        1: begin
          if (clk1 == 1 && clk2 == 1) begin
                dataDMC <= data_first;
            end
          else if (clk1 == 1 && clk2 == 0) begin
                dataDMC <= ~data_first;
            end
        end
        0: begin
          if (clk1 == 1 && clk2 == 1) begin
                dataDMC <= ~data_first;
            end
          else if (clk1 == 1 && clk2 == 0) begin
                dataDMC <= ~data_first;
            end
        end
        default: begin
            dataDMC <= 0;
        end
    endcase
  end

 
endmodule

//Module dividir signal Clock
module Clock_divider#(parameter WIDTH = 16)(
			input logic 	clk1,
  			input logic    nrst,
			output logic 	clk2
);
  logic aux;
  always_ff @(posedge clk1 or negedge nrst) begin

    if(~nrst) begin
      aux <= 0;
    end
    else begin
      aux = ~ aux;
    end
end
  assign clk2 = aux;
  
endmodule

SP4-SPDIF-AES3/tb/testbench.sv
module SPDIF_tb;
  
  // Specifying time units for the simulation
  timeunit 1ns;
  timeprecision 1ps;

  // DUT signals
  localparam int WIDTH = 16;
  logic out, clk1, nrst, dataDMC, clk2, data;
  //logic [WIDTH-1:0] data;
  
  //DUT
  SPDIF #(.WIDTH(WIDTH)
         ) DUT (.clk1(clk1),
                .clk2(clk2),
                .nrst(nrst),
                .data(data),
                .dataDMC(dataDMC)
 );
  
  Clock_divider #(.WIDTH(WIDTH)
                 )DUT2 (.clk1(clk1),
                        .nrst(nrst),
                        .clk2(clk2)
 );
  
  //Clock
  initial begin
    repeat(15)
    begin #1 clk1 = ~clk1;end
  end
  
  //Initiate Test
 initial begin
        clk1 = 0;
   		nrst = 0;
   		data = 1;
     	#0.1 nrst = 1;
		#1 data = 1;
   		#1 data = 1;
   		#1 data = 1;
   		#1 data = 0;
   		#1 data = 1;
   		#1 data = 0;
        #1 data = 0;
        #1 data = 0;
   		#1 data = 0;
   		#1 data = 1;
   		//data = 11'b11110100001;
   		//data = 11'b11110100001;
		# 15 $finish;
 end
  //Dump
    initial begin
      $dumpfile("dump.vcd");
      $dumpvars(1, SPDIF_tb);
      $monitor("TIME:%g, CLK2F= %g:, CLK1F:%d, DATA_IN:%d, DATA_OUT:%d.", $time, clk2, clk1, data, dataDMC);
    end
  
endmodule

SP4-SPDIF-AES3/tb/dump.vcd
$date
    Apr 24, 2024  14:09:36
$end
$version
    TOOL:	xmsim	20.09-s003
$end
$timescale
    1 ps
$end

$scope module SPDIF_tb $end
$var parameter 32 !    WIDTH $end
$var reg       1 "    out $end
$var reg       1 #    clk1 $end
$var reg       1 $    nrst $end
$var reg       1 %    dataDMC $end
$var reg       1 &    clk2 $end
$var reg       1 '    data $end
$upscope $end

$enddefinitions $end
$dumpvars
b10000 !
x"
0#
0$
0%
0&
1'
$end
#100
1$
#1000
1#
1&
#2000
0#
#3000
1#
0&
1%
#4000
0#
#4100
0'
#5000
1#
1&
0%
#5100
1'
1%
#6000
0#
#6100
0'
#7000
1#
0&
0%
#8000
0#
#9000
1#
1&
1%
#10000
0#
#10100
1'
#11000
1#
0&
0%
#12000
0#
#13000
1#
1&
#14000
0#
#15000
1#
0&
1%
